libname/VFunctions.py
libname/__init__.py
VFunctions-0.0.3.dist-info/METADATA
VFunctions-0.0.3.dist-info/WHEEL
VFunctions-0.0.3.dist-info/top_level.txt
VFunctions-0.0.3.dist-info/RECORD
