Metadata-Version: 2.1
Name: VFunctions
Version: 0.0.3
Summary: Some things that will make my work easier
Author: sonkraft1
Author-email: <skraft2727@gmail.com>
License: UNKNOWN
Keywords: python
Platform: UNKNOWN
